cairocffi-stubs/__init__.pyi
cairocffi-stubs/constants.pyi
cairocffi-stubs/context.pyi
cairocffi-stubs/ffi_build.pyi
cairocffi-stubs/fonts.pyi
cairocffi-stubs/matrix.pyi
cairocffi-stubs/patterns.pyi
cairocffi-stubs/pixbuf.pyi
cairocffi-stubs/surfaces.pyi
cairocffi-stubs/xcb.pyi
cairocffi_stubs-0.1.2.dist-info/WHEEL
cairocffi_stubs-0.1.2.dist-info/METADATA
cairocffi_stubs-0.1.2.dist-info/RECORD
